{
  "template": {
    "type": "JSON",
    "content": [
      {
        "id": "4067509",
        "Flight": "F9114",
        "Time": "15:12",
        "HotelName": "Planet Hollywood Cancun"
      },
      {
        "id": "9896SE630204",
        "Flight": "AA1132",
        "Time": "15:05",
        "HotelName": "Planet Hollywood Cancun"
      },
      {
        "id": "3587952",
        "Flight": "WS2309",
        "Time": "15:45",
        "HotelName": "Planet Hollywood Cancun"
      },
      {
        "id": "1J2WHK",
        "Flight": "WN1608",
        "Time": "12:45",
        "HotelName": "Planet Hollywood Cancun"
      },
      {
        "id": "9896SE649296",
        "Flight": "WS2209",
        "Time": "18:00",
        "HotelName": "Planet Hollywood Cancun"
      },
      {
        "id": "9896SE649846",
        "Flight": "TBA000",
        "Time": "00:00",
        "HotelName": "Contact your Planet Experience Rep"
      },
      {
        "id": "140501605",
        "Flight": "WG5114",
        "Time": "10:25",
        "HotelName": "Planet Hollywood Cancun"
      },
      {
        "id": "9896SE626256",
        "Flight": "TBA000",
        "Time": "00:00",
        "HotelName": "Contact your Planet Experience Rep"
      },
      {
        "id": "9896SE649994",
        "Flight": "TBA000",
        "Time": "15:00",
        "HotelName": "Contact your Planet Experience Rep"
      },
      {
        "id": "4067509",
        "Flight": "F9114",
        "Time": "15:12",
        "HotelName": "Planet Hollywood Cancun"
      },
      {
        "id": "3581914",
        "Flight": "WS2309",
        "Time": "15:45",
        "HotelName": "Planet Hollywood Cancun"
      },
      {
        "id": "9896SE659594",
        "Flight": "WN180",
        "Time": "15:25",
        "HotelName": "Planet Hollywood Cancun"
      },
      {
        "id": "141207393",
        "Flight": "WG5182",
        "Time": "14:50",
        "HotelName": "Planet Hollywood Cancun"
      },
      {
        "id": "9896SE659930",
        "Flight": "TBA000",
        "Time": "15:00",
        "HotelName": "Contact your Planet Experience Rep"
      },
      {
        "id": "9896SE652350",
        "Flight": "TBA000",
        "Time": "15:00",
        "HotelName": "Contact your Planet Experience Rep"
      },
      {
        "id": "9896SE593189",
        "Flight": "TBA000",
        "Time": "15:00",
        "HotelName": "Contact your Planet Experience Rep"
      },
      {
        "id": "9896SE659934",
        "Flight": "TBA000",
        "Time": "15:00",
        "HotelName": "Contact your Planet Experience Rep"
      },
      {
        "id": "9896SE626261",
        "Flight": "TBA000",
        "Time": "00:00",
        "HotelName": "Contact your Planet Experience Rep"
      },
      {
        "id": "3597478",
        "Flight": "WS2209",
        "Time": "18:00",
        "HotelName": "Planet Hollywood Cancun"
      },
      {
        "id": "3597703",
        "Flight": "WS2209",
        "Time": "18:00",
        "HotelName": "Planet Hollywood Cancun"
      },
      {
        "id": "9896SE667001",
        "Flight": "TBA000",
        "Time": "03:00",
        "HotelName": "Contact your Planet Experience Rep"
      },
      {
        "id": "9896SF697043",
        "Flight": "DL1878",
        "Time": "14:00",
        "HotelName": "Planet Hollywood Cancun"
      },
      {
        "id": "140501625",
        "Flight": "WG5182",
        "Time": "14:50",
        "HotelName": "Planet Hollywood Cancun"
      },
      {
        "id": "DNG5Y4",
        "Flight": "F945",
        "Time": "10:43",
        "HotelName": "Planet Hollywood Cancun"
      },
      {
        "id": "141664693",
        "Flight": "WG512",
        "Time": "21:05",
        "HotelName": "Planet Hollywood Cancun"
      },
      {
        "id": "139453942",
        "Flight": "WG5182",
        "Time": "14:50",
        "HotelName": "Planet Hollywood Cancun"
      },
      {
        "id": "140461425",
        "Flight": "WG5164",
        "Time": "14:35",
        "HotelName": "Planet Hollywood Cancun"
      },
      {
        "id": "140417903",
        "Flight": "WG552",
        "Time": "14:55",
        "HotelName": "Planet Hollywood Cancun"
      },
      {
        "id": "9896SE492995",
        "Flight": "F990",
        "Time": "10:50",
        "HotelName": "Planet Hollywood Cancun"
      },
      {
        "id": "141581273",
        "Flight": "WG5164",
        "Time": "14:35",
        "HotelName": "Planet Hollywood Cancun"
      },
      {
        "id": "4068203",
        "Flight": "F9114",
        "Time": "15:12",
        "HotelName": "Planet Hollywood Cancun"
      },
      {
        "id": "140024773",
        "Flight": "WG5164",
        "Time": "14:35",
        "HotelName": "Planet Hollywood Cancun"
      },
      {
        "id": "9896SF709006",
        "Flight": "TBA000",
        "Time": "00:00",
        "HotelName": "Contact your Planet Experience Rep"
      },
      {
        "id": "9896SE593189",
        "Flight": "TBA000",
        "Time": "00:00",
        "HotelName": "Contact your Planet Experience Rep"
      },
      {
        "id": "3597478",
        "Flight": "WS2209",
        "Time": "18:00",
        "HotelName": "Planet Hollywood Cancun"
      },
      {
        "id": "9896SE620873",
        "Flight": "UA1056",
        "Time": "13:43",
        "HotelName": "Planet Hollywood Cancun"
      },
      {
        "id": "9896SE674696",
        "Flight": "TBA000",
        "Time": "00:00",
        "HotelName": "Contact your Planet Experience Rep"
      },
      {
        "id": "R31PTS",
        "Flight": "UA1058",
        "Time": "17:22",
        "HotelName": "Planet Hollywood Cancun"
      },
      {
        "id": "9896SE648309",
        "Flight": "AA1723",
        "Time": "16:30",
        "HotelName": "Planet Hollywood Cancun"
      },
      {
        "id": "3597582",
        "Flight": "WS2209",
        "Time": "18:00",
        "HotelName": "Planet Hollywood Cancun"
      },
      {
        "id": "141207872",
        "Flight": "WG5182",
        "Time": "14:50",
        "HotelName": "Planet Hollywood Cancun"
      },
      {
        "id": "9896SE659845",
        "Flight": "TBA000",
        "Time": "15:00",
        "HotelName": "Contact your Planet Experience Rep"
      },
      {
        "id": "3633883",
        "Flight": "WS2413",
        "Time": "16:15",
        "HotelName": "Planet Hollywood Cancun"
      },
      {
        "id": "3587927",
        "Flight": "WS2309",
        "Time": "15:45",
        "HotelName": "Planet Hollywood Cancun"
      },
      {
        "id": "9896SE631528",
        "Flight": "TBA000",
        "Time": "00:00",
        "HotelName": "Contact your Planet Experience Rep"
      },
      {
        "id": "3633123",
        "Flight": "WS2263",
        "Time": "12:30",
        "HotelName": "Planet Hollywood Cancun"
      },
      {
        "id": "3597135",
        "Flight": "WS2209",
        "Time": "18:00",
        "HotelName": "Planet Hollywood Cancun"
      },
      {
        "id": "9896SF690468",
        "Flight": "TBA000",
        "Time": "15:00",
        "HotelName": "Contact your Planet Experience Rep"
      },
      {
        "id": "9896SE492996",
        "Flight": "F990",
        "Time": "10:50",
        "HotelName": "Planet Hollywood Cancun"
      },
      {
        "id": "4265453",
        "Flight": "WN0348",
        "Time": "16:10",
        "HotelName": "Planet Hollywood Cancun"
      },
      {
        "id": "9896SE492986",
        "Flight": "UA1051",
        "Time": "13:12",
        "HotelName": "Planet Hollywood Cancun"
      },
      {
        "id": "9896SE650244",
        "Flight": "TBA000",
        "Time": "15:00",
        "HotelName": "Contact your Planet Experience Rep"
      },
      {
        "id": "9896SE633239",
        "Flight": "B6122",
        "Time": "12:40",
        "HotelName": "Planet Hollywood Cancun"
      },
      {
        "id": "141699152",
        "Flight": "WG5182",
        "Time": "14:50",
        "HotelName": "Planet Hollywood Cancun"
      },
      {
        "id": "9896SE633271",
        "Flight": "TBA000",
        "Time": "00:00",
        "HotelName": "Contact your Planet Experience Rep"
      },
      {
        "id": "141354881",
        "Flight": "WG552",
        "Time": "14:55",
        "HotelName": "Planet Hollywood Cancun"
      },
      {
        "id": "139454152",
        "Flight": "WG5182",
        "Time": "14:50",
        "HotelName": "Planet Hollywood Cancun"
      }
    ],
    "source": {
      "data_source": "Google Sheets (Private)",
      "update_frequency": "Automated"
    }
  }
}